psd2svg/__init__.py
psd2svg/__main__.py
psd2svg/eval.py
psd2svg/font_subsetting.py
psd2svg/image_utils.py
psd2svg/py.typed
psd2svg/resource_limits.py
psd2svg/svg_document.py
psd2svg/svg_utils.py
psd2svg/timeout_utils.py
psd2svg/version.py
psd2svg/core/__init__.py
psd2svg/core/_font_mapping_data.py
psd2svg/core/adjustment.py
psd2svg/core/base.py
psd2svg/core/color_utils.py
psd2svg/core/constants.py
psd2svg/core/converter.py
psd2svg/core/counter.py
psd2svg/core/effects.py
psd2svg/core/font_mapping.py
psd2svg/core/font_utils.py
psd2svg/core/gradient.py
psd2svg/core/layer.py
psd2svg/core/paint.py
psd2svg/core/shape.py
psd2svg/core/text.py
psd2svg/core/typesetting.py
psd2svg/core/windows_fonts.py
psd2svg/data/__init__.py
psd2svg/data/default_fonts.json
psd2svg/data/morisawa_fonts.json
psd2svg/rasterizer/__init__.py
psd2svg/rasterizer/base_rasterizer.py
psd2svg/rasterizer/playwright_rasterizer.py
psd2svg/rasterizer/resvg_rasterizer.py
psd2svg/tools/__init__.py
psd2svg/tools/__main__.py
psd2svg/tools/generate_font_mapping.py
psd2svg-0.11.0.dist-info/METADATA
psd2svg-0.11.0.dist-info/WHEEL
psd2svg-0.11.0.dist-info/entry_points.txt
psd2svg-0.11.0.dist-info/licenses/LICENSE
psd2svg-0.11.0.dist-info/RECORD
