Metadata-Version: 2.4
Name: psd2svg
Version: 0.11.0
Summary: Convert PSD file to SVG file
Project-URL: Homepage, https://github.com/kyamagu/psd2svg
Project-URL: Repository, https://github.com/kyamagu/psd2svg
Author-email: "CyberAgent, Inc." <yamaguchi_kota@cyberagent.co.jp>
License-Expression: MIT
License-File: LICENSE
Keywords: photoshop,psd,svg
Classifier: Development Status :: 4 - Beta
Classifier: License :: OSI Approved :: MIT License
Classifier: Programming Language :: Python :: 3.10
Classifier: Programming Language :: Python :: 3.11
Classifier: Programming Language :: Python :: 3.12
Classifier: Programming Language :: Python :: 3.13
Classifier: Programming Language :: Python :: 3.14
Classifier: Topic :: Multimedia :: Graphics
Classifier: Topic :: Multimedia :: Graphics :: Graphics Conversion
Classifier: Topic :: Multimedia :: Graphics :: Viewers
Requires-Python: <3.15,>=3.10
Requires-Dist: fontconfig-py>=0.4.0; sys_platform != 'win32'
Requires-Dist: fonttools[woff]>=4.60.2
Requires-Dist: numpy
Requires-Dist: pillow
Requires-Dist: psd-tools>=1.12.0
Requires-Dist: resvg-py>=0.2.5
Provides-Extra: browser
Requires-Dist: playwright>=1.40.0; extra == 'browser'
